mm_secretkeeper/__init__.py
mm_secretkeeper/config.py
mm_secretkeeper/keeper.py
mm_secretkeeper/web.py
mm_secretkeeper/cli/__init__.py
mm_secretkeeper/cli/cli.py
mm_secretkeeper/cli/daemon.py
mm_secretkeeper-0.0.3.dist-info/METADATA
mm_secretkeeper-0.0.3.dist-info/WHEEL
mm_secretkeeper-0.0.3.dist-info/entry_points.txt
mm_secretkeeper-0.0.3.dist-info/RECORD
