Metadata-Version: 2.4
Name: mm-secretkeeper
Version: 0.0.3
Summary: a secret keeper
Requires-Python: >=3.13
Requires-Dist: fastapi[all]~=0.115.6
Requires-Dist: mm-std~=0.1.11
Requires-Dist: pyperclip~=1.9.0
Requires-Dist: python-daemon==3.1.2
Requires-Dist: sqlcipher3~=0.5.4
Requires-Dist: typer~=0.15.1
